dockerimagepack/__init__.py
dockerimagepack/__main__.py
dockerimagepack/dockertool.py
dockerimagepack/packfile.py
dockerimagepack/tool.py
dockerimagepack/utils.py
docker_image_pack-0.0.1.dist-info/LICENSE
docker_image_pack-0.0.1.dist-info/METADATA
docker_image_pack-0.0.1.dist-info/WHEEL
docker_image_pack-0.0.1.dist-info/entry_points.txt
docker_image_pack-0.0.1.dist-info/top_level.txt
docker_image_pack-0.0.1.dist-info/RECORD
