Metadata-Version: 2.1
Name: docker-image-pack
Version: 0.0.1
Summary: Manage docker images for offline use
Home-page: https://gitlab.com/cunity/docker-image-pack
Author: Ian Norton
Author-email: inorton@gmail.com
Classifier: Development Status :: 4 - Beta
Classifier: Intended Audience :: Developers
Classifier: Topic :: Software Development :: Build Tools
Classifier: License :: OSI Approved :: MIT License
Classifier: Programming Language :: Python :: 3.8
Classifier: Programming Language :: Python :: 3.9
Classifier: Programming Language :: Python :: 3.10
Classifier: Programming Language :: Python :: 3 :: Only
Requires-Python: >=3.8, <4
License-File: LICENSE
